{
  "m_GameObject": {
    "m_FileID": 0,
    "m_PathID": 0
  },
  "m_Enabled": 1,
  "m_Script": {
    "m_FileID": 0,
    "m_PathID": 8302033850027404168
  },
  "m_Name": "cookie0517_emotion_SkeletonData",
  "atlasAssets": [
    {
      "m_FileID": 0,
      "m_PathID": -8044493026715340042
    }
  ],
  "scale": 1.0,
  "skeletonJSON": {
    "m_FileID": 0,
    "m_PathID": -7817169400888296191
  },
  "skeletonDataModifiers": [],
  "fromAnimation": [],
  "toAnimation": [],
  "duration": [],
  "defaultMix": 0.0,
  "controller": {
    "m_FileID": 0,
    "m_PathID": 0
  }
}