{
  "m_GameObject": {
    "m_FileID": 0,
    "m_PathID": -7490764135508524198
  },
  "m_Enabled": 1,
  "m_Script": {
    "m_FileID": 0,
    "m_PathID": 6631733874144873996
  },
  "m_Name": "",
  "_completeStateObjects": [
    {
      "m_FileID": 0,
      "m_PathID": 501575493364819169
    }
  ],
  "_normalStateObjects": [
    {
      "m_FileID": 0,
      "m_PathID": 6640080158172847107
    }
  ],
  "_rewardedStateObjects": [
    {
      "m_FileID": 0,
      "m_PathID": 6640080158172847107
    },
    {
      "m_FileID": 0,
      "m_PathID": -4808595089984429429
    },
    {
      "m_FileID": 0,
      "m_PathID": -3264110532107852579
    }
  ],
  "_button": {
    "m_FileID": 0,
    "m_PathID": 0
  }
}