{
  "m_GameObject": {
    "m_FileID": 0,
    "m_PathID": 4417508460643796887
  },
  "m_Enabled": 1,
  "m_Script": {
    "m_FileID": 0,
    "m_PathID": 803187770610367623
  },
  "m_Name": "",
  "_targetImage": {
    "m_FileID": 0,
    "m_PathID": 1453752811284355506
  },
  "_localizationImageInfos": [
    {
      "_gameLanguage": 2,
      "_image": {
        "m_FileID": 0,
        "m_PathID": 4520050059000282668
      }
    },
    {
      "_gameLanguage": 1,
      "_image": {
        "m_FileID": 0,
        "m_PathID": 4362522162021233246
      }
    },
    {
      "_gameLanguage": 3,
      "_image": {
        "m_FileID": 0,
        "m_PathID": -7312056297584508793
      }
    },
    {
      "_gameLanguage": 5,
      "_image": {
        "m_FileID": 0,
        "m_PathID": 5521440157502058923
      }
    },
    {
      "_gameLanguage": 10,
      "_image": {
        "m_FileID": 0,
        "m_PathID": 2839771861831746785
      }
    }
  ]
}