{
  "m_GameObject": {
    "m_FileID": 0,
    "m_PathID": 8362247999066177871
  },
  "m_Enabled": 1,
  "m_Script": {
    "m_FileID": 0,
    "m_PathID": 803187770610367623
  },
  "m_Name": "",
  "_targetImage": {
    "m_FileID": 0,
    "m_PathID": 544925702545742743
  },
  "_localizationImageInfos": [
    {
      "_gameLanguage": 2,
      "_image": {
        "m_FileID": 0,
        "m_PathID": 2419871848024458617
      }
    },
    {
      "_gameLanguage": 1,
      "_image": {
        "m_FileID": 0,
        "m_PathID": 4790840570845378636
      }
    },
    {
      "_gameLanguage": 3,
      "_image": {
        "m_FileID": 0,
        "m_PathID": 1084204533825749617
      }
    },
    {
      "_gameLanguage": 5,
      "_image": {
        "m_FileID": 0,
        "m_PathID": 1877212980451112459
      }
    },
    {
      "_gameLanguage": 10,
      "_image": {
        "m_FileID": 0,
        "m_PathID": 8123430570741550177
      }
    }
  ]
}