{
  "m_GameObject": {
    "m_FileID": 0,
    "m_PathID": 845006390503433091
  },
  "m_Enabled": 1,
  "m_Script": {
    "m_FileID": 0,
    "m_PathID": 803187770610367623
  },
  "m_Name": "",
  "_targetImage": {
    "m_FileID": 0,
    "m_PathID": -2226311805493726872
  },
  "_localizationImageInfos": [
    {
      "_gameLanguage": 2,
      "_image": {
        "m_FileID": 0,
        "m_PathID": -2105771056778895332
      }
    },
    {
      "_gameLanguage": 1,
      "_image": {
        "m_FileID": 0,
        "m_PathID": -7717128788117501574
      }
    },
    {
      "_gameLanguage": 3,
      "_image": {
        "m_FileID": 0,
        "m_PathID": -8080611898091885302
      }
    },
    {
      "_gameLanguage": 5,
      "_image": {
        "m_FileID": 0,
        "m_PathID": -1582546061223025025
      }
    },
    {
      "_gameLanguage": 10,
      "_image": {
        "m_FileID": 0,
        "m_PathID": 7291341196004434355
      }
    }
  ]
}