{
  "m_GameObject": {
    "m_FileID": 0,
    "m_PathID": 0
  },
  "m_Enabled": 1,
  "m_Script": {
    "m_FileID": 0,
    "m_PathID": 8302033850027404168
  },
  "m_Name": "npc0024_SkeletonData",
  "atlasAssets": [
    {
      "m_FileID": 0,
      "m_PathID": -2076906475593560863
    }
  ],
  "scale": 1.0,
  "skeletonJSON": {
    "m_FileID": 0,
    "m_PathID": 6525978659657101093
  },
  "skeletonDataModifiers": [],
  "fromAnimation": [],
  "toAnimation": [],
  "duration": [],
  "defaultMix": 0.0,
  "controller": {
    "m_FileID": 0,
    "m_PathID": 0
  }
}